README.rst
setup.py
django_redmine_models.egg-info/PKG-INFO
django_redmine_models.egg-info/SOURCES.txt
django_redmine_models.egg-info/dependency_links.txt
django_redmine_models.egg-info/not-zip-safe
django_redmine_models.egg-info/requires.txt
django_redmine_models.egg-info/top_level.txt
redmine_models/__init__.py
redmine_models/models.py
redmine_models/routers.py