Metadata-Version: 1.1
Name: django-redmine-models
Version: 0.2
Summary: Django models for the Redmine database.
Home-page: https://github.com/zvin/django-redmine-models
Author: Alexis Svinartchouk
Author-email: UNKNOWN
License: BSD
Platform: UNKNOWN
Classifier: Development Status :: 5 - Production/Stable
Classifier: Intended Audience :: Developers
Classifier: License :: OSI Approved :: BSD License
Classifier: Operating System :: OS Independent
Classifier: Programming Language :: Python
Classifier: Programming Language :: Python :: 2
Classifier: Programming Language :: Python :: 2.7
Classifier: Topic :: Utilities
Classifier: Framework :: Django
Classifier: Topic :: Software Development :: Libraries :: Python Modules
Classifier: Topic :: Office/Business :: Groupware
Classifier: Topic :: Internet :: WWW/HTTP :: Site Management
Requires: django (>=1.7)
